[
    {
        "collection_id": 0,
        "nfts": [
            {
                "name": "Caravan #754",
                "id": "00",
                "price": 0.0179,
                "description": "Curious Cabins No. 50 — Caravan\nCurious Cabins is a collection of isometric houses, hand drawn by Stefan Große Halbuer. No. 50 is a special Open Edition, to celebrate the world of Curious Cabins.",
                "imageUrl": "https://i.seadn.io/gcs/files/e2ac0c7bc990af763892ee7a4d1e1f7e.jpg?auto=format&w=1000",
                "owner": "ferhatznv"
            },
            {
                "name": "Caravan #357",
                "id": "10",
                "price": 0.025,
                "description": "Curious Cabins No. 50 — Caravan\nCurious Cabins is a collection of isometric houses, hand drawn by Stefan Große Halbuer. No. 50 is a special Open Edition, to celebrate the world of Curious Cabins.",
                "imageUrl": "https://i.seadn.io/gcs/files/7921fe91226f374551b0e47a7aaba537.jpg?auto=format&dpr=1&w=1000",
                "owner": "Permabearish2"
            },
            {
                "name": "Caravan #584",
                "id": "20",
                "price": 0.02,
                "description": "Curious Cabins No. 50 — Caravan\nCurious Cabins is a collection of isometric houses, hand drawn by Stefan Große Halbuer. No. 50 is a special Open Edition, to celebrate the world of Curious Cabins.",
                "imageUrl": "https://i.seadn.io/gcs/files/1edc9880fbd445994c0237243d3b7d13.jpg?auto=format&w=1000",
                "owner": "lordcalder"
            },
            {
                "name": "Caravan #586",
                "id": "30",
                "price": 0.02,
                "description": "Curious Cabins No. 50 — Caravan\nCurious Cabins is a collection of isometric houses, hand drawn by Stefan Große Halbuer. No. 50 is a special Open Edition, to celebrate the world of Curious Cabins.",
                "imageUrl": "https://i.seadn.io/gcs/files/63f944ec7134bf5b5608538ee6e6a286.jpg?auto=format&w=1000",
                "owner": "lordcalder"
            }
        ]
    },
    {
        "collection_id": 1,
        "nfts": [
            {
                "name": "#9307",
                "id": "01",
                "price": 49.85,
                "description": "",
                "imageUrl": "https://i.seadn.io/gae/zqp0Pue2YYOK6cUnZoELfq_bwaIs00Q0blIfQJyRR0Ka1pR26Z_iphnP6IDsEqyOFWEZ5f1Qs1Jnn0ipvudF8RcxZN69qGgsBMQw?auto=format&w=1000",
                "owner": "jesipinkman"
            },
            {
                "name": "#4284",
                "id": "11",
                "price": 49.8765,
                "description": "",
                "imageUrl": "https://i.seadn.io/gae/7eevo_iOngjOQ0swesO-Ll8Ua5p0kzCuYlamp0vDuC2jJO_kTBfjt9T-983e5gUAISUSJCln2rayZilsSxHMgWpRgO4f00HVPr1s?auto=format&w=1000",
                "owner": "8ED9A2"
            },
            {
                "name": "#2382",
                "id": "21",
                "price": 48,
                "description": "",
                "imageUrl": "https://i.seadn.io/gae/UZ9trsMF2D5zEucUN89bH6Rw-ANgxPw0G6fyYGXmRLd8lidakhx189kxCbg7Y0_t0-xh_cnH_xawHOjM7uCO1h0HJiSbWW6oBjj64g?auto=format&dpr=1&w=1000",
                "owner": "ferhatznv"
            },
            {
                "name": "#7717",
                "id": "31",
                "price": 50,
                "description": "",
                "imageUrl": "https://i.seadn.io/gae/k5Br_2-cOHFs440w-mOZSkCp870jtYT48R3gmDHuiWyxJQJCb6_srOCve4WqG1aBkTDg4pFzxcENWojvd-0d3Fd3KBEwiEIJU9sxxqM?auto=format&w=1000",
                "owner": "Permabearish2"
            },
            {
                "name": "#9106",
                "id": "41",
                "price": 51.96,
                "description": "",
                "imageUrl": "https://i.seadn.io/gae/5JTdZZxeEGsJtZuJEtbm8_C1IwbO3fLRbNmLeNs60M3U9IE9w4P2YIqGZdBJkr0HzdYkfE3d4WMEoNSAtzifCxIynQ_ujmAaOmI3FQ?auto=format&w=1000",
                "owner": "EEB57A"
            }
        ]
    },
    {
        "collection_id": 2,
        "nfts": [
            {
                "name": "DeadFellaz #8714",
                "id": "02",
                "price": 0.24 ,
                "description": "Owning an NFT from the Deadfellaz 10K grants you access to one of the most innovative and trusted brands in Web3. The utility of DFZ is constantly evolving through multiple developments within metaverse, interoperability, digital identity & Web3 tech. DF token ownership comes with non-exclusive IP rights to the likeness of the artwork. IP ownership details are available on www.deadfellaz.io",
                "imageUrl": "https://i.seadn.io/gcs/files/a37b17493420cb321cf1d0243cf91229.png?auto=format&w=1000",
                "owner": "KillaBee4"
            },
            {
                "name": "DeadFellaz #4466",
                "id": "12",
                "price": 0.279,
                "description": "Owning an NFT from the Deadfellaz 10K grants you access to one of the most innovative and trusted brands in Web3. The utility of DFZ is constantly evolving through multiple developments within metaverse, interoperability, digital identity & Web3 tech. DF token ownership comes with non-exclusive IP rights to the likeness of the artwork. IP ownership details are available on www.deadfellaz.io",
                "imageUrl": "https://i.seadn.io/gcs/files/2e00b4d38394d21441e734e72f1f69d3.png?auto=format&w=1000",
                "owner": "VoidSeeker"
            },
            {
                "name": "DeadFellaz #1272",
                "id": "22",
                "price": 0.299,
                "description": "Owning an NFT from the Deadfellaz 10K grants you access to one of the most innovative and trusted brands in Web3. The utility of DFZ is constantly evolving through multiple developments within metaverse, interoperability, digital identity & Web3 tech. DF token ownership comes with non-exclusive IP rights to the likeness of the artwork. IP ownership details are available on www.deadfellaz.io",
                "imageUrl": "https://i.seadn.io/gcs/files/50a5cb4a4c4662ba65669e703f8d61a0.png?auto=format&w=1000",
                "owner": "DeadhandNFT"
            },
            {
                "name": "DeadFellaz #5692",
                "id": "32",
                "price": 0.28,
                "description": "Owning an NFT from the Deadfellaz 10K grants you access to one of the most innovative and trusted brands in Web3. The utility of DFZ is constantly evolving through multiple developments within metaverse, interoperability, digital identity & Web3 tech. DF token ownership comes with non-exclusive IP rights to the likeness of the artwork. IP ownership details are available on www.deadfellaz.io",
                "imageUrl": "https://i.seadn.io/gcs/files/cc2443624e3434cab141e72493898d83.png?auto=format&w=1000",
                "owner": "Shruuump2"
            },
            {
                "name": "DeadFellaz #6986",
                "id": "42",
                "price": 0.2667,
                "description": "Owning an NFT from the Deadfellaz 10K grants you access to one of the most innovative and trusted brands in Web3. The utility of DFZ is constantly evolving through multiple developments within metaverse, interoperability, digital identity & Web3 tech. DF token ownership comes with non-exclusive IP rights to the likeness of the artwork. IP ownership details are available on www.deadfellaz.io",
                "imageUrl": "https://i.seadn.io/gcs/files/8382635122846ba516e9520319ed8d56.png?auto=format&dpr=1&w=1000",
                "owner": "lordcalder"
            }
        ]
    }
]